{
    "username": "trubond_user",
    "password": "OjB4UyqH0L9R3ByAmk1oaol66TcBAG9z",
    "database": "trubond",
    "host": "dpg-cstmdm68ii6s73fkk7qg-a.singapore-postgres.render.com",
    "dialect": "postgres",
    "logging": false,
    "pool": {
        "max": 10,
        "min": 0,
        "acquire": 30000,
        "idle": 10000
    },
    "port": 5432,
    "dialectOptions": {
        "ssl": {
            "require": true,
            "rejectUnauthorized": false
        }
    },
    "seederStorage": "sequelize",
    "seederStorageTableName": "SequelizeData"
}
